paramsdict/__init__.py
paramsdict/paramsdict.py
paramsdict/util.py
paramsdict-0.0.3.dist-info/LICENSE
paramsdict-0.0.3.dist-info/METADATA
paramsdict-0.0.3.dist-info/WHEEL
paramsdict-0.0.3.dist-info/top_level.txt
paramsdict-0.0.3.dist-info/RECORD
