Metadata-Version: 2.1
Name: paramsdict
Version: 0.0.3
Summary: User-friendly parameter dictionaries in Python
Home-page: https://github.com/adamoppenheimer/paramsdict/
Author: Adam A. Oppenheimer
Author-email: adam.a.oppenheimer@gmail.com
Project-URL: GitHub, https://github.com/adamoppenheimer/paramsdict/
Classifier: Programming Language :: Python :: 3
Classifier: License :: OSI Approved :: MIT License
Classifier: Operating System :: OS Independent
Requires-Python: >=3.6
License-File: LICENSE
Requires-Dist: numpy
Requires-Dist: pandas
